shared_utils/__init__.py
shared_utils/jwt_authentication.py
shared_utils/pagination.py
shared_utils/permissions.py
shared_utils/update_model.py
shared_utils/exception/__init__.py
shared_utils/exception/exception_handler.py
shared_utils/exception/exceptions.py
shared_utils_ems-4.2.0.dist-info/METADATA
shared_utils_ems-4.2.0.dist-info/WHEEL
shared_utils_ems-4.2.0.dist-info/top_level.txt
shared_utils_ems-4.2.0.dist-info/RECORD
