Metadata-Version: 2.2
Name: shared-utils-ems
Version: 4.2.0
Summary: A shared utility library for event management system based on microservices architecture.
Home-page: https://github.com/imansadati/event_management_system
Author: iman sadati
Author-email: iman.3adati@gmail.com
Classifier: Programming Language :: Python :: 3
Classifier: Operating System :: OS Independent
Dynamic: author
Dynamic: author-email
Dynamic: classifier
Dynamic: description
Dynamic: description-content-type
Dynamic: home-page
Dynamic: summary
